ZijiDongshouzuoLiaotianJiqiren/README.md
ZijiDongshouzuoLiaotianJiqiren/__init__.py
ZijiDongshouzuoLiaotianJiqiren/__main__.py
ZijiDongshouzuoLiaotianJiqiren/file.epub
ZijiDongshouzuoLiaotianJiqiren/index.html
ZijiDongshouzuoLiaotianJiqiren/css/__init__.py
ZijiDongshouzuoLiaotianJiqiren/css/annotations.css
ZijiDongshouzuoLiaotianJiqiren/css/main.css
ZijiDongshouzuoLiaotianJiqiren/css/normalize.css
ZijiDongshouzuoLiaotianJiqiren/css/popup.css
ZijiDongshouzuoLiaotianJiqiren/font/__init__.py
ZijiDongshouzuoLiaotianJiqiren/font/fontello.eot
ZijiDongshouzuoLiaotianJiqiren/font/fontello.svg
ZijiDongshouzuoLiaotianJiqiren/font/fontello.ttf
ZijiDongshouzuoLiaotianJiqiren/font/fontello.woff
ZijiDongshouzuoLiaotianJiqiren/img/__init__.py
ZijiDongshouzuoLiaotianJiqiren/img/annotator-glyph-sprite.png
ZijiDongshouzuoLiaotianJiqiren/img/annotator-icon-sprite.png
ZijiDongshouzuoLiaotianJiqiren/img/apple-touch-icon.png
ZijiDongshouzuoLiaotianJiqiren/img/cancelfullscreen.png
ZijiDongshouzuoLiaotianJiqiren/img/close.png
ZijiDongshouzuoLiaotianJiqiren/img/fullscreen.png
ZijiDongshouzuoLiaotianJiqiren/img/loader.gif
ZijiDongshouzuoLiaotianJiqiren/img/menu-icon.png
ZijiDongshouzuoLiaotianJiqiren/img/save.png
ZijiDongshouzuoLiaotianJiqiren/img/saved.png
ZijiDongshouzuoLiaotianJiqiren/img/settings-s.png
ZijiDongshouzuoLiaotianJiqiren/img/settings.png
ZijiDongshouzuoLiaotianJiqiren/img/star.png
ZijiDongshouzuoLiaotianJiqiren/js/__init__.py
ZijiDongshouzuoLiaotianJiqiren/js/epub.js
ZijiDongshouzuoLiaotianJiqiren/js/epub.min.js
ZijiDongshouzuoLiaotianJiqiren/js/epub.min.map
ZijiDongshouzuoLiaotianJiqiren/js/hooks.min.js
ZijiDongshouzuoLiaotianJiqiren/js/hooks.min.map
ZijiDongshouzuoLiaotianJiqiren/js/reader.js
ZijiDongshouzuoLiaotianJiqiren/js/reader.js.map
ZijiDongshouzuoLiaotianJiqiren/js/reader.min.js
ZijiDongshouzuoLiaotianJiqiren/js/reader.min.map
ZijiDongshouzuoLiaotianJiqiren/js/hooks/__init__.py
ZijiDongshouzuoLiaotianJiqiren/js/hooks/extensions/__init__.py
ziji_dongshouzuo_liaotian_jiqiren-2024.3.3.0.dist-info/METADATA
ziji_dongshouzuo_liaotian_jiqiren-2024.3.3.0.dist-info/WHEEL
ziji_dongshouzuo_liaotian_jiqiren-2024.3.3.0.dist-info/entry_points.txt
ziji_dongshouzuo_liaotian_jiqiren-2024.3.3.0.dist-info/top_level.txt
ziji_dongshouzuo_liaotian_jiqiren-2024.3.3.0.dist-info/RECORD
